{
  "phase": 1,
  "phase_name": "task.md -- Topic picker and state.json updates",
  "started_at": "2026-05-15T00:05:00Z",
  "last_updated": "2026-05-15T00:15:00Z",
  "objectives": [
    {"id": 1, "description": "Insert Step 4.5 (topic picker) after Step 4 (task_type detection)", "status": "done"},
    {"id": 2, "description": "Update Step 6 (state.json update) to include --arg topic and conditional topic field", "status": "done"},
    {"id": 3, "description": "Replace Part C old update-recommended-order.sh call with generate-task-order.sh --update-todo", "status": "done"}
  ],
  "current_objective": 3,
  "approaches_tried": [],
  "handoff_count": 0,
  "deviations": []
}
